amntftp/__init__.py
amntftp/client.py
amntftp/consts.py
amntftp/server.py
amntftp-0.1.1.dist-info/LICENSE
amntftp-0.1.1.dist-info/METADATA
amntftp-0.1.1.dist-info/WHEEL
amntftp-0.1.1.dist-info/top_level.txt
amntftp-0.1.1.dist-info/RECORD
