Metadata-Version: 2.1
Name: amntftp
Version: 0.1.1
Summary: AmmuNation TFTP protocol
Home-page: https://github.com/munshigroup/amntftp
Author: The Munshi Group
Author-email: support@munshigroup.com
License: UNKNOWN
Platform: UNKNOWN
Classifier: Programming Language :: Python :: 2.7
Classifier: License :: OSI Approved :: MIT License
Classifier: Operating System :: OS Independent
Requires-Dist: lair3
Requires-Dist: kthread
